jrag/__init__.py
jrag/jrag.py
jrag-0.0.1.dist-info/licenses/LICENSE
jrag-0.0.1.dist-info/METADATA
jrag-0.0.1.dist-info/WHEEL
jrag-0.0.1.dist-info/top_level.txt
jrag-0.0.1.dist-info/RECORD
