Metadata-Version: 2.4
Name: jrag
Version: 0.0.1
Summary: Convert json to string for RAG applications.
Author: Cormac Rynne
License: Copyright (c) 2025 Cormac Rynne
Project-URL: Homepage, https://github.com/cormac-rynne/jrag/
Project-URL: Repository, https://github.com/cormac-rynne/jrag/
Project-URL: Bug Tracker, https://github.com/cormac-rynne/jrag/issues
Classifier: Programming Language :: Python :: 3
Requires-Python: >=3.8
License-File: LICENSE
Requires-Dist: jsonpath_ng
Provides-Extra: dev
Requires-Dist: pytest>=7.0; extra == "dev"
Requires-Dist: pytest-cov; extra == "dev"
Requires-Dist: flake8>=5.0; extra == "dev"
Requires-Dist: flake8-pyproject; extra == "dev"
Requires-Dist: black>=22.0; extra == "dev"
Requires-Dist: python-semantic-release>=8.0; extra == "dev"
Requires-Dist: build>=0.10; extra == "dev"
Requires-Dist: twine>=4.0; extra == "dev"
Requires-Dist: wheel; extra == "dev"
Requires-Dist: setuptools; extra == "dev"
Requires-Dist: pip-audit; extra == "dev"
Requires-Dist: pre-commit>=3.0; extra == "dev"
Dynamic: license-file
